README.md
setup.py
SiMon/__init__.py
SiMon/demo_simulation_code.py
SiMon/ic_generator.py
SiMon/ic_generator_demo.py
SiMon/module_common.py
SiMon/module_demo_simulation.py
SiMon/simon.py
SiMon/utilities.py
SiMon/tests/__init__.py
SiMon/tests/test_simon.py
astrosimon.egg-info/PKG-INFO
astrosimon.egg-info/SOURCES.txt
astrosimon.egg-info/dependency_links.txt
astrosimon.egg-info/entry_points.txt
astrosimon.egg-info/not-zip-safe
astrosimon.egg-info/requires.txt
astrosimon.egg-info/top_level.txt