Metadata-Version: 1.0
Name: astrosimon
Version: 0.8.5
Summary: Simulation Monitor for computational astrophysics
Home-page: https://github.com/maxwelltsai/SiMon
Author: Maxwell Cai, Penny Qian
Author-email: maxwellemail@gmail.com
License: BSD 2-Clause
Platform: UNKNOWN
